naml/__init__.py
naml/plot.py
naml/sequence.py
naml/text.py
naml/util.py
naml/modules/__init__.py
naml/modules/attention.py
naml/modules/encoding.py
naml/modules/init.py
naml/modules/sequence.py
naml/modules/transformer.py
naml/modules/utils.py
naml-0.0.4.dist-info/METADATA
naml-0.0.4.dist-info/WHEEL
naml-0.0.4.dist-info/top_level.txt
naml-0.0.4.dist-info/RECORD
