Metadata-Version: 2.1
Name: naml
Version: 0.0.4
Summary: Naml is Another Machine Learning library (better name pending)
Home-page: https://github.com/mos9527/naml
Author: mos9527
Author-email: greats3an@gmail.com
Classifier: Programming Language :: Python :: 3
Classifier: License :: OSI Approved :: Apache Software License
Classifier: Operating System :: OS Independent
Requires-Python: ~=3.10
Requires-Dist: matplotlib==3.10.1
Requires-Dist: numpy==2.2.3
Requires-Dist: scipy==1.15.2
Requires-Dist: sympy==1.13.1
Requires-Dist: torch==2.6.0
Requires-Dist: torchaudio==2.6.0
Requires-Dist: torchvision==0.21.0
Requires-Dist: nbformat
Requires-Dist: tqdm
Requires-Dist: requests
Requires-Dist: pytest
Requires-Dist: ipywidgets
